drf_compose/__init__.py
drf_compose/cli.py
drf_compose/django_core/__init__.py
drf_compose/django_core/settings.py
drf_compose/django_template_app/__init__.py
drf_compose/django_template_app/apps.py
drf_compose/django_template_app/templates/app/admin.py-tpl
drf_compose/django_template_app/templates/app/app_urls.py-tpl
drf_compose/django_template_app/templates/app/apps.py-tpl
drf_compose/django_template_app/templates/app/models.py-tpl
drf_compose/django_template_app/templates/app/serializers.py-tpl
drf_compose/django_template_app/templates/app/views.py-tpl
drf_compose/django_template_app/templates/auth_app/admin.py-tpl
drf_compose/django_template_app/templates/auth_app/auth_urls.py-tpl
drf_compose/django_template_app/templates/auth_app/manager.py-tpl
drf_compose/django_template_app/templates/auth_app/models.py-tpl
drf_compose/django_template_app/templates/auth_app/serializers.py-tpl
drf_compose/django_template_app/templates/auth_app/views.py-tpl
drf_compose/django_template_app/templates/project_level/project_urls.py-tpl
drf_compose/django_template_app/templates/project_level/requirements.txt-tpl
drf_compose/django_template_app/templates/project_level/settings.py-tpl
drf_compose/django_template_app/templatetags/myfilters.py
drf_compose-0.1.1.dist-info/AUTHORS.rst
drf_compose-0.1.1.dist-info/LICENSE
drf_compose-0.1.1.dist-info/METADATA
drf_compose-0.1.1.dist-info/WHEEL
drf_compose-0.1.1.dist-info/entry_points.txt
drf_compose-0.1.1.dist-info/top_level.txt
drf_compose-0.1.1.dist-info/RECORD
