Metadata-Version: 2.1
Name: drf-compose
Version: 0.1.1
Summary: DRF Compose generates ready to use API using Django Rest Framework
Home-page: https://github.com/IamAbbey/drf_compose
Author: Sotunde Abiodun
Author-email: sotundeabiodun00@gmail.com
License: BSD license
Keywords: drf_compose
Platform: UNKNOWN
Classifier: Development Status :: 2 - Pre-Alpha
Classifier: Intended Audience :: Developers
Classifier: License :: OSI Approved :: BSD License
Classifier: Natural Language :: English
Classifier: Programming Language :: Python :: 3
Classifier: Programming Language :: Python :: 3.6
Classifier: Programming Language :: Python :: 3.7
Classifier: Programming Language :: Python :: 3.8
Requires-Python: >=3.6
License-File: LICENSE
License-File: AUTHORS.rst
Requires-Dist: Click (==8.0)
Requires-Dist: Django (==3.2.7)
Requires-Dist: django-cors-headers (==3.8.0)
Requires-Dist: djangorestframework (==3.12.4)
Requires-Dist: drf-yasg (==1.20.0)
Requires-Dist: emoji (==1.4.2)
Requires-Dist: PyYAML (==5.4.1)
Requires-Dist: black (==21.7b0)
